setup.cfg
setup.py
rajaongkir/__init__.py
rajaongkir/api.py
rajaongkir.egg-info/PKG-INFO
rajaongkir.egg-info/SOURCES.txt
rajaongkir.egg-info/dependency_links.txt
rajaongkir.egg-info/top_level.txt