Metadata-Version: 1.1
Name: rajaongkir
Version: 1.1.1
Summary: Simple Python module to grab api data from rajaongkir.com
Home-page: https://github.com/slaveofcode/rajaongkir
Author: Aditya Kresna Permana
Author-email: zeandcode@gmail.com
License: UNKNOWN
Download-URL: https://github.com/slaveofcode/rajaongkir/archive/v1.1.0.zip
Keywords: ongkir,rajaongkir,JNE,TIKI,Pos
Platform: UNKNOWN
